Metadata-Version: 2.1
Name: NCPLQ
Version: 0.0.2
Summary: A nice and simple library for everything you may need
Home-page: UNKNOWN
Author: Nishaanth Reddy Jaishobha
Author-email: nishaanthreddyjaishobha@gmail.com
License: MIT
Platform: UNKNOWN
Classifier: Development Status :: 5 - Production/Stable
Classifier: Intended Audience :: Education
Classifier: Operating System :: Microsoft :: Windows :: Windows 10
Classifier: License :: OSI Approved :: MIT License
Classifier: Programming Language :: Python :: 3
License-File: LICENSE.txt
